mtcleanse/__init__.py
mtcleanse/bin/__init__.py
mtcleanse/bin/clean_cli.py
mtcleanse/cleaning/__init__.py
mtcleanse/cleaning/clean.py
mtcleanse/cleaning/config.py
mtcleanse/cleaning/filters.py
mtcleanse/cleaning/kiwi_filter.py
mtcleanse/cleaning/report.py
mtcleanse/cleaning/stats.py
mtcleanse/cleaning/templates/report.html
mtcleanse/utils/__init__.py
mtcleanse/utils/file_utils.py
mtcleanse/utils/logging.py
tests/__init__.py
tests/test_cleaner.py
mtcleanse-0.2.1.dist-info/LICENSE
mtcleanse-0.2.1.dist-info/METADATA
mtcleanse-0.2.1.dist-info/WHEEL
mtcleanse-0.2.1.dist-info/entry_points.txt
mtcleanse-0.2.1.dist-info/top_level.txt
mtcleanse-0.2.1.dist-info/RECORD
