Metadata-Version: 2.2
Name: mtcleanse
Version: 0.2.1
Summary: Machine Translation Corpus Cleaning and Processing
Home-page: https://github.com/Ancastal/mtcleanse
Author: Antonio Castaldo
Author-email: antonio.castaldo@phd.unipi.it
Project-URL: Bug Tracker, https://github.com/Ancastal/mtcleanse/issues
Classifier: Programming Language :: Python :: 3
Classifier: License :: OSI Approved :: MIT License
Classifier: Operating System :: OS Independent
Classifier: Development Status :: 4 - Beta
Classifier: Intended Audience :: Science/Research
Classifier: Topic :: Scientific/Engineering :: Artificial Intelligence
Classifier: Topic :: Text Processing :: Linguistic
Requires-Python: >=3.7
License-File: LICENSE
Requires-Dist: numpy>=1.19.0
Requires-Dist: torch>=1.7.0
Requires-Dist: scikit-learn>=0.24.0
Requires-Dist: sentence-transformers>=2.0.0
Requires-Dist: rich>=10.0.0
Requires-Dist: tqdm>=4.50.0
Requires-Dist: jinja2>=3.0.0
Requires-Dist: plotly>=5.0.0
Provides-Extra: dev
Requires-Dist: pytest>=7.0.0; extra == "dev"
Requires-Dist: pytest-cov>=4.0.0; extra == "dev"
Requires-Dist: black>=23.0.0; extra == "dev"
Requires-Dist: isort>=5.0.0; extra == "dev"
Requires-Dist: flake8>=6.0.0; extra == "dev"
Requires-Dist: build>=0.10.0; extra == "dev"
Requires-Dist: twine>=4.0.0; extra == "dev"
Requires-Dist: pre-commit>=3.0.0; extra == "dev"
Provides-Extra: quality
Requires-Dist: unbabel-comet>=2.0.0; extra == "quality"
Dynamic: author
Dynamic: author-email
Dynamic: classifier
Dynamic: description
Dynamic: description-content-type
Dynamic: home-page
Dynamic: project-url
Dynamic: provides-extra
Dynamic: requires-dist
Dynamic: requires-python
Dynamic: summary
